{
  "openapi": "3.0.1",
  "info": {
    "title": "Greenops",
    "version": "1.0"
  },
  "paths": {
    "/api/Complaint/register": {
      "post": {
        "tags": [
          "Complaint"
        ],
        "requestBody": {
          "content": {
            "application/json": {
              "schema": {
                "$ref": "#/components/schemas/Complaint"
              }
            },
            "text/json": {
              "schema": {
                "$ref": "#/components/schemas/Complaint"
              }
            },
            "application/*+json": {
              "schema": {
                "$ref": "#/components/schemas/Complaint"
              }
            }
          }
        },
        "responses": {
          "200": {
            "description": "OK"
          }
        }
      }
    },
    "/api/Complaint/all": {
      "get": {
        "tags": [
          "Complaint"
        ],
        "responses": {
          "200": {
            "description": "OK"
          }
        }
      }
    },
    "/api/Feedback/submit": {
      "post": {
        "tags": [
          "Feedback"
        ],
        "requestBody": {
          "content": {
            "application/json": {
              "schema": {
                "$ref": "#/components/schemas/Feedback"
              }
            },
            "text/json": {
              "schema": {
                "$ref": "#/components/schemas/Feedback"
              }
            },
            "application/*+json": {
              "schema": {
                "$ref": "#/components/schemas/Feedback"
              }
            }
          }
        },
        "responses": {
          "200": {
            "description": "OK"
          }
        }
      }
    },
    "/api/Feedback/all": {
      "get": {
        "tags": [
          "Feedback"
        ],
        "responses": {
          "200": {
            "description": "OK"
          }
        }
      }
    },
    "/api/Order/buy": {
      "post": {
        "tags": [
          "Order"
        ],
        "requestBody": {
          "content": {
            "application/json": {
              "schema": {
                "$ref": "#/components/schemas/Order"
              }
            },
            "text/json": {
              "schema": {
                "$ref": "#/components/schemas/Order"
              }
            },
            "application/*+json": {
              "schema": {
                "$ref": "#/components/schemas/Order"
              }
            }
          }
        },
        "responses": {
          "200": {
            "description": "OK"
          }
        }
      }
    },
    "/api/Order/user/{userId}": {
      "get": {
        "tags": [
          "Order"
        ],
        "parameters": [
          {
            "name": "userId",
            "in": "path",
            "required": true,
            "schema": {
              "type": "integer",
              "format": "int32"
            }
          }
        ],
        "responses": {
          "200": {
            "description": "OK"
          }
        }
      }
    },
    "/api/Resale/add": {
      "post": {
        "tags": [
          "Resale"
        ],
        "requestBody": {
          "content": {
            "application/json": {
              "schema": {
                "$ref": "#/components/schemas/ResaleItem"
              }
            },
            "text/json": {
              "schema": {
                "$ref": "#/components/schemas/ResaleItem"
              }
            },
            "application/*+json": {
              "schema": {
                "$ref": "#/components/schemas/ResaleItem"
              }
            }
          }
        },
        "responses": {
          "200": {
            "description": "OK"
          }
        }
      }
    },
    "/api/Resale/items": {
      "get": {
        "tags": [
          "Resale"
        ],
        "responses": {
          "200": {
            "description": "OK"
          }
        }
      }
    },
    "/api/Resale/user/{userId}": {
      "get": {
        "tags": [
          "Resale"
        ],
        "parameters": [
          {
            "name": "userId",
            "in": "path",
            "required": true,
            "schema": {
              "type": "integer",
              "format": "int32"
            }
          }
        ],
        "responses": {
          "200": {
            "description": "OK"
          }
        }
      }
    },
    "/api/WasteReport/report": {
      "post": {
        "tags": [
          "WasteReport"
        ],
        "requestBody": {
          "content": {
            "application/json": {
              "schema": {
                "$ref": "#/components/schemas/WasteReport"
              }
            },
            "text/json": {
              "schema": {
                "$ref": "#/components/schemas/WasteReport"
              }
            },
            "application/*+json": {
              "schema": {
                "$ref": "#/components/schemas/WasteReport"
              }
            }
          }
        },
        "responses": {
          "200": {
            "description": "OK"
          }
        }
      }
    },
    "/api/WasteReport/all": {
      "get": {
        "tags": [
          "WasteReport"
        ],
        "responses": {
          "200": {
            "description": "OK"
          }
        }
      }
    }
  },
  "components": {
    "schemas": {
      "Complaint": {
        "type": "object",
        "properties": {
          "complaintId": {
            "type": "integer",
            "format": "int32"
          },
          "userId": {
            "type": "integer",
            "format": "int32"
          },
          "complaintDescription": {
            "type": "string",
            "nullable": true
          },
          "proofImage": {
            "type": "string",
            "nullable": true
          },
          "complaintDate": {
            "type": "string",
            "format": "date-time"
          },
          "status": {
            "type": "string",
            "nullable": true
          }
        },
        "additionalProperties": false
      },
      "Feedback": {
        "type": "object",
        "properties": {
          "feedbackId": {
            "type": "integer",
            "format": "int32"
          },
          "userId": {
            "type": "integer",
            "format": "int32"
          },
          "feedbackContent": {
            "type": "string",
            "nullable": true
          },
          "submittedDate": {
            "type": "string",
            "format": "date-time"
          }
        },
        "additionalProperties": false
      },
      "Order": {
        "type": "object",
        "properties": {
          "orderId": {
            "type": "integer",
            "format": "int32"
          },
          "productId": {
            "type": "integer",
            "format": "int32"
          },
          "buyerId": {
            "type": "integer",
            "format": "int32"
          },
          "sellerId": {
            "type": "integer",
            "format": "int32"
          },
          "productPrice": {
            "type": "number",
            "format": "double"
          },
          "orderDate": {
            "type": "string",
            "format": "date-time"
          },
          "orderStatus": {
            "type": "string",
            "nullable": true
          }
        },
        "additionalProperties": false
      },
      "ResaleItem": {
        "type": "object",
        "properties": {
          "productId": {
            "type": "integer",
            "format": "int32"
          },
          "userId": {
            "type": "integer",
            "format": "int32"
          },
          "productName": {
            "type": "string",
            "nullable": true
          },
          "productDetails": {
            "type": "string",
            "nullable": true
          },
          "usageYears": {
            "type": "integer",
            "format": "int32"
          },
          "productPrice": {
            "type": "number",
            "format": "double"
          },
          "productImage": {
            "type": "string",
            "nullable": true
          },
          "postedDate": {
            "type": "string",
            "format": "date-time"
          },
          "productStatus": {
            "type": "string",
            "nullable": true
          }
        },
        "additionalProperties": false
      },
      "WasteReport": {
        "type": "object",
        "properties": {
          "reportId": {
            "type": "integer",
            "format": "int32"
          },
          "userId": {
            "type": "integer",
            "format": "int32"
          },
          "district": {
            "type": "string",
            "nullable": true
          },
          "place": {
            "type": "string",
            "nullable": true
          },
          "description": {
            "type": "string",
            "nullable": true
          },
          "wasteImage": {
            "type": "string",
            "nullable": true
          },
          "reportDate": {
            "type": "string",
            "format": "date-time"
          }
        },
        "additionalProperties": false
      }
    }
  }
}